{
  "1": {
    "1": {
      "name": "room",
      "data": [
        "salt",
        "sock",
        "strawberry",
        "tomato",
        "towel"
      ],
      "duration": 120
    },
    "2": {
      "name": "listening",
      "data": [
        "salt",
        "sock",
        "strawberry",
        "tomato",
        "towel",
        "word_s",
        "word_t",
        "word_S",
        "word_T"
      ],
      "duration": 120
    },
    "3": {
      "name": "writing",
      "data": [
        "word_s",
        "word_t",
        "word_S",
        "word_T"
      ],
      "duration": 240
    },
    "4": {
      "name": "writing",
      "data": [
        "word_s",
        "word_t",
        "word_S",
        "word_T"
      ],
      "duration": 240
    },
    "5": {
      "name": "writing",
      "data": [
        "word_s",
        "word_t",
        "word_S",
        "word_T"
      ],
      "duration": 240
    },
    "6": {
      "name": "speaking",
      "data": [
        "word_s",
        "word_t",
        "word_S",
        "word_T"
      ],
      "duration": 240
    }
  },
  "2": {
    "1": {
      "name": "forest",
      "data": [
        "scorpion",
        "seal",
        "shark",
        "sheep",
        "snail"
      ],
      "duration": 120
    },
    "2": {
      "name": "listening",
      "data": [
        "scorpion",
        "seal",
        "shark",
        "sheep",
        "snail"
      ],
      "duration": 60
    },
    "3": {
      "name": "writing",
      "data": [
        "scorpion",
        "seal",
        "shark",
        "sheep",
        "snail"
      ],
      "duration": 240
    },
    "4": {
      "name": "writing",
      "data": [
        "scorpion",
        "seal",
        "shark",
        "sheep",
        "snail"
      ],
      "duration": 240
    },
    "5": {
      "name": "writing",
      "data": [
        "scorpion",
        "seal",
        "shark",
        "sheep",
        "snail"
      ],
      "duration": 240
    },
    "6": {
      "name": "speaking",
      "data": [
        "scorpion",
        "seal",
        "shark",
        "sheep",
        "snail"
      ],
      "duration": 120
    }
  },
  "3": {
    "1": {
      "name": "fruiddition",
      "data": {
        "type": [
          "banana",
          "apple"
        ],
        "data": [
          {
            "first": [
              "number_10",
              "number_2",
              "number_8",
              "number_1"
            ],
            "second": [
              "number_3",
              "number_4",
              "number_5",
              "number_6"
            ],
            "third": [
              "number_7",
              "number_6",
              "number_3",
              "number_7"
            ],
            "firstOperation": [
              "sub",
              "plus",
              "sub",
              "plus"
            ],
            "secondOperation": [
              "equal",
              "equal",
              "equal",
              "equal"
            ]
          }
        ]
      },
      "duration": 180
    },
    "2": {
      "name": "listening-fruiddition",
      "data": [],
      "duration": 120
    },
    "3": {
      "name": "writing-fruiddition",
      "data": [],
      "duration": 180
    },
    "4": {
      "name": "speaking-fruiddition",
      "data": [],
      "duration": 120
    }
  },
  "4": {
    "1": {
      "name": "buildingblocks",
      "data": {
        "type": "block",
        "data": [
          {
            "first": [
              [
                "number_1",
                "number_3"
              ],
              [
                "number_10",
                "number_9"
              ],
              [
                "number_3",
                "number_4"
              ],
              [
                "number_10",
                "number_6"
              ]
            ],
            "second": [
              [
                "number_5",
                "number_3"
              ],
              [
                "number_3",
                "number_2"
              ],
              [
                "number_5",
                "number_4"
              ],
              [
                "number_5",
                "number_1"
              ]
            ],
            "third": [
              "number_6",
              "number_7",
              "number_8",
              "number_5"
            ],
            "firstOperation": [
              "plus",
              "sub",
              "plus",
              "sub"
            ],
            "secondOperation": [
              "equal",
              "equal",
              "equal",
              "equal"
            ]
          }
        ]
      },
      "duration": 180
    },
    "2": {
      "name": "listening-buildingblocks",
      "data": [
        {
          "first": [
            [
              "number_1"
            ],
            [
              "number_3"
            ],
            [
              "number_10"
            ],
            [
              "number_9"
            ],
            [
              "number_3"
            ],
            [
              "number_4"
            ],
            [
              "number_10"
            ],
            [
              "number_6"
            ]
          ],
          "second": [
            [
              "number_5"
            ],
            [
              "number_3"
            ],
            [
              "number_3"
            ],
            [
              "number_2"
            ],
            [
              "number_5"
            ],
            [
              "number_4"
            ],
            [
              "number_5"
            ],
            [
              "number_1"
            ]
          ],
          "third": [
            "number_6",
            "number_6",
            "number_7",
            "number_7",
            "number_8",
            "number_8",
            "number_5",
            "number_5"
          ],
          "firstOperation": [
            "plus",
            "plus",
            "sub",
            "sub",
            "plus",
            "plus",
            "sub",
            "sub"
          ],
          "secondOperation": [
            "equal",
            "equal",
            "equal",
            "equal",
            "equal",
            "equal",
            "equal",
            "equal"
          ]
        }
      ],
      "duration": 120
    },
    "3": {
      "name": "writing-buildingblocks",
      "data": [
        {
          "first": [
            [
              "number_1"
            ],
            [
              "number_3"
            ],
            [
              "number_10"
            ],
            [
              "number_9"
            ],
            [
              "number_3"
            ],
            [
              "number_4"
            ],
            [
              "number_10"
            ],
            [
              "number_6"
            ]
          ],
          "second": [
            [
              "number_5"
            ],
            [
              "number_3"
            ],
            [
              "number_3"
            ],
            [
              "number_2"
            ],
            [
              "number_5"
            ],
            [
              "number_4"
            ],
            [
              "number_5"
            ],
            [
              "number_1"
            ]
          ],
          "third": [
            "number_6",
            "number_6",
            "number_7",
            "number_7",
            "number_8",
            "number_8",
            "number_5",
            "number_5"
          ],
          "firstOperation": [
            "plus",
            "plus",
            "sub",
            "sub",
            "plus",
            "plus",
            "sub",
            "sub"
          ],
          "secondOperation": [
            "equal",
            "equal",
            "equal",
            "equal",
            "equal",
            "equal",
            "equal",
            "equal"
          ]
        }
      ],
      "duration": 180
    },
    "4": {
      "name": "speaking-buildingblocks",
      "data": [
        {
          "third": [
            "number_6",
            "number_6",
            "number_7",
            "number_7",
            "number_8",
            "number_8",
            "number_5",
            "number_5"
          ],
          "sentences": [
          ]
        }
      ],
      "duration": 120
    }
  },
  "5": {
    "1": {
      "name": "balloon",
      "data": [
        {
          "type": "word",
          "value": "S",
          "amount": "10"
        },
        {
          "type": "word",
          "value": "s",
          "amount": "10"
        },
        {
          "type": "word",
          "value": "T",
          "amount": "10"
        },
        {
          "type": "word",
          "value": "t",
          "amount": "10"
        }
      ],
      "duration": 120
    },
    "2": {
      "name": "listening",
      "data": [
        "word_S",
        "word_s",
        "word_T",
        "word_t"
      ],
      "duration": 60
    },
    "3": {
      "name": "writing",
      "data": [
        "word_S",
        "word_s",
        "word_T",
        "word_t"
      ],
      "duration": 240
    },
    "4": {
      "name": "writing",
      "data": [
        "word_S",
        "word_s",
        "word_T",
        "word_t"
      ],
      "duration": 240
    },
    "5": {
      "name": "writing",
      "data": [
        "word_S",
        "word_s",
        "word_T",
        "word_t"
      ],
      "duration": 240
    },
    "6": {
      "name": "writing",
      "data": [
        "word_S",
        "word_s",
        "word_T",
        "word_t"
      ],
      "duration": 120
    }
  }
}