{
  "1": {
    "1": {
      "name": "room",
      "data": [
        "nail",
        "nest",
        "pen",
        "pencils",
        "potato",
        "queen"
      ],
      "duration": 120
    },
    "2": {
      "name": "listening",
      "data": [
        "nail",
        "nest",
        "pen",
        "pencils",
        "potato",
        "queen",
        "n",
        "p",
        "q",
        "N",
        "P",
        "Q"
      ],
      "duration": 120
    },
    "3": {
      "name": "speaking",
      "data": [
        "nail",
        "nest",
        "pen",
        "pencils",
        "potato",
        "queen",
        "n",
        "p",
        "q",
        "N",
        "P",
        "Q"
      ],
      "duration": 120
    },
    "4": {
      "name": "writing",
      "data": [
        "n",
        "p",
        "q",
        "N",
        "P",
        "Q"
      ],
      "duration": 240
    }
  },
  "2": {
    "1": {
      "name": "forest",
      "data": [
        "panda",
        "pig",
        "puppy",
        "rabbit",
        "rat"
      ],
      "duration": 120
    },
    "2": {
      "name": "listening",
      "data": [
        "panda",
        "pig",
        "puppy",
        "rabbit",
        "rat",
        "P",
        "R",
        "p",
        "r"
      ],
      "duration": 120
    },
    "3": {
      "name": "writing",
      "data": [
        "panda",
        "pig",
        "puppy",
        "rabbit",
        "rat",
        "P",
        "R",
        "p",
        "r"
      ],
      "duration": 240
    },
    "4": {
      "name": "writing",
      "data": [
        "panda",
        "pig",
        "puppy",
        "rabbit",
        "rat",
        "P",
        "R",
        "p",
        "r"
      ],
      "duration": 240
    },
    "5": {
      "name": "writing",
      "data": [
        "panda",
        "pig",
        "puppy",
        "rabbit",
        "rat",
        "P",
        "R",
        "p",
        "r"
      ],
      "duration": 240
    },
    "6": {
      "name": "speaking",
      "data": [
        "panda",
        "pig",
        "puppy",
        "rabbit",
        "rat",
        "P",
        "R",
        "p",
        "r"
      ],
      "duration": 120
    }
  },
  "3": {
    "1": {
      "name": "fruiddition",
      "data": {
        "type": "banana",
        "data": [
          {
            "first": [
              "number_5",
              "number_4",
              "number_3",
              "number_2"
            ],
            "second": [
              "number_1",
              "number_1",
              "number_1",
              "number_1"
            ],
            "third": [
              "number_4",
              "number_3",
              "number_2",
              "number_1"
            ],
            "firstOperation": [
              "sub",
              "sub",
              "sub",
              "sub"
            ],
            "secondOperation": [
              "equal",
              "equal",
              "equal",
              "equal"
            ]
          }
        ]
      },
      "duration": 180
    },
    "2": {
      "name": "speaking-fruiddition",
      "data": [],
      "duration": 120
    }
  },
  "4": {
    "1": {
      "name": "buildingblocks",
      "data": {
        "type": "block",
        "data": [
              {
                "first": [
                  ["number_1", "number_3"],
                  ["number_2", "number_3"],
                  ["number_3", "number_4"],
                  ["number_4", "number_3"]
                ],
                "second": [
                  ["number_4", "number_3"],
                  ["number_5", "number_4"],
                  ["number_5", "number_4"],
                  ["number_5", "number_6"]
                ],
                "third": [
                  "number_6",
                  "number_7",
                  "number_8",
                  "number_9"
                ],
                "firstOperation": [
                  "plus",
                  "plus",
                  "plus",
                  "plus"
                ],
                "secondOperation": [
                  "equal",
                  "equal",
                  "equal",
                  "equal"
                ]
              }
            ]
      },
      "duration": 120
    },
    "2": {
      "name": "listening-buildingblocks",
      "data": [],
      "duration": 60
    },
    "3": {
      "name": "writing-buildingblocks",
      "data": [],
      "duration": 180
    },
    "4": {
      "name": "speaking-buildingblocks",
      "data": [],
      "duration": 120
    }
  },
  "5": {
    "1": {
      "name": "balloon",
      "data": [
        {
          "type": "word",
          "value": "N",
          "amount": "10"
        },
        {
          "type": "word",
          "value": "n",
          "amount": "10"
        },
        {
          "type": "word",
          "value": "p",
          "amount": "10"
        },
        {
          "type": "word",
          "value": "P",
          "amount": "10"
        }
      ],
      "duration": 240
    },
    "2": {
      "name": "listening",
      "data": [],
      "duration": 60
    },
    "3": {
      "name": "writing",
      "data": [],
      "duration": 240
    },
    "4": {
      "name": "writing",
      "data": [],
      "duration": 240
    },
    "5": {
      "name": "writing",
      "data": [],
      "duration": 240
    },
    "6": {
      "name": "speaking",
      "data": [],
      "duration": 120
    }
  }
}